authparser/__init__.py
authparser/authparser.py
authparser-1.1.dist-info/LICENSE
authparser-1.1.dist-info/METADATA
authparser-1.1.dist-info/WHEEL
authparser-1.1.dist-info/top_level.txt
authparser-1.1.dist-info/RECORD
