Metadata-Version: 2.1
Name: authparser
Version: 1.1
Summary: Used to parse http Authentication headers, and to call handlers per scheme.
Home-page: https://github.com/pointw-dev/authparser
Author: Michael Ottoson
Author-email: michael@pointw.com
License: MIT
Platform: UNKNOWN
Classifier: Programming Language :: Python :: 3
Classifier: License :: OSI Approved :: MIT License
Classifier: Operating System :: OS Independent
Requires-Dist: pyparsing
